ShellyPy/__init__.py
ShellyPy/base.py
ShellyPy/error.py
ShellyPy/gen1.py
ShellyPy/gen2.py
ShellyPy/wrapper.py
ShellyPy-0.3.0.dist-info/LICENSE
ShellyPy-0.3.0.dist-info/METADATA
ShellyPy-0.3.0.dist-info/WHEEL
ShellyPy-0.3.0.dist-info/top_level.txt
ShellyPy-0.3.0.dist-info/RECORD
