Metadata-Version: 2.1
Name: ShellyPy
Version: 0.3.0
Summary: Wrapper around the Shelly HTTP api
Home-page: https://github.com/Jan200101/ShellyPy
Author: Jan Drögehoff
Author-email: jandroegehoff@gmail.com
License: MIT
Classifier: Programming Language :: Python :: 2
Classifier: Programming Language :: Python :: 3
Classifier: License :: OSI Approved :: MIT License
Classifier: Operating System :: OS Independent
License-File: LICENSE
Requires-Dist: requests
